README.md
cmwalk/SubDir_CMakeLists.txt.jinja2
cmwalk/TopLevel_CMakeLists.txt.jinja2
cmwalk/__init__.py
cmwalk/cmwalk.py
cmwalk/version.py
cmwalk-0.1.0.dist-info/DESCRIPTION.rst
cmwalk-0.1.0.dist-info/METADATA
cmwalk-0.1.0.dist-info/RECORD
cmwalk-0.1.0.dist-info/WHEEL
cmwalk-0.1.0.dist-info/entry_points.txt
cmwalk-0.1.0.dist-info/metadata.json
cmwalk-0.1.0.dist-info/top_level.txt
