Metadata-Version: 2.0
Name: cmwalk
Version: 0.1.0
Summary: A python script to walk subdirectories of a C/C++ project of embedded system to generate CMakeLists.txt files for building the executable.
Home-page: https://github.com/maxpeng/cmWalk
Author: Max Peng
Author-email: max.peng1768@gmail.com
License: MIT
Keywords: cmake
Platform: UNKNOWN
Requires-Dist: jinja2
Requires-Dist: walkdir
